{
  "entry": "Models\\N_Beats_Model_v3.py",
  "images": [
    "C:\\Users\\anikk\\BioNet\\to py\\Results\\images\\N_Beats_Model_v3\\Hungary\\summer\\training_loss_plot_summer_nbeats_v3.png",
    "C:\\Users\\anikk\\BioNet\\to py\\Results\\images\\N_Beats_Model_v3\\Hungary\\summer\\forecast_examples_summer_nbeats_v3.png"
  ],
  "season": "summer",
  "cwd": "C:\\Users\\anikk\\BioNet\\to py",
  "metrics": {
    "mae": 12.735623895380645,
    "mse": 223.82387598504943,
    "rmse": 14.960744499691499,
    "mape": 0.545960987425039
  },
  "emissions_csv": "C:\\Users\\anikk\\BioNet\\to py\\Results\\emissions\\N_Beats_Model_v3\\Hungary\\summer\\N_Beats_Model_v3_Hungary_summer_run1_emissions.csv"
}